pageflow/__init__.py
pageflow/_compat.py
pageflow/baidu.py
pageflow/base.py
pageflow/bing.py
pageflow/cx_extractor.py
pageflow/google.py
pageflow/pages.py
pageflow/result.py
pageflow/utils.py
pageflow-0.1.dist-info/LICENSE
pageflow-0.1.dist-info/METADATA
pageflow-0.1.dist-info/WHEEL
pageflow-0.1.dist-info/top_level.txt
pageflow-0.1.dist-info/RECORD
