Metadata-Version: 2.1
Name: pageflow
Version: 0.1
Summary: Simple, powerful and pythonic web page search results crawler.
Home-page: https://github.com/lapis-hong/PageFlow
Author: Lapis-Hong
Author-email: dhq1125@163.com
License: MIT
Keywords: pageflow,search result spider,web information extraction
Platform: UNKNOWN
Classifier: Intended Audience :: Developers
Classifier: Natural Language :: English
Classifier: License :: OSI Approved :: MIT License
Classifier: Programming Language :: Python
Classifier: Programming Language :: Python :: 2.7
Classifier: Programming Language :: Python :: 3.4
Classifier: Programming Language :: Python :: 3.5
Classifier: Programming Language :: Python :: 3.6
Classifier: Programming Language :: Python :: Implementation :: CPython
Classifier: Programming Language :: Python :: Implementation :: PyPy
Classifier: Topic :: Text Processing
Requires-Dist: requests (>=2.12)
Requires-Dist: scrapy (>=1.6.0)
Requires-Dist: cchardet
